pygametemplate/__init__.py
pygametemplate/_game.py
pygametemplate/_image.py
pygametemplate/_view.py
pygametemplate/button.py
pygametemplate/console.py
pygametemplate/core.py
pygametemplate/exceptions.py
pygametemplate/helper.py
pygametemplate/hotkey.py
pygametemplate/system.py
pygametemplate/text_input.py
pygametemplate/userinput.py
pygametemplate-0.9.2.dist-info/DESCRIPTION.rst
pygametemplate-0.9.2.dist-info/METADATA
pygametemplate-0.9.2.dist-info/RECORD
pygametemplate-0.9.2.dist-info/WHEEL
pygametemplate-0.9.2.dist-info/metadata.json
pygametemplate-0.9.2.dist-info/top_level.txt
