Metadata-Version: 2.0
Name: pygametemplate
Version: 0.9.2
Summary: Making making games with Pygame easier :)
Home-page: https://github.com/AndyDeany/pygame-template
Author: Andrew Dean
Author-email: oneandydean@hotmail.com
License: MIT
Download-URL: https://github.com/AndyDeany/pygame-template/archive/v0.9.2.tar.gz
Keywords: pygame,template,gamedev
Platform: UNKNOWN
Classifier: Development Status :: 2 - Pre-Alpha
Classifier: Intended Audience :: Developers
Classifier: Natural Language :: English
Classifier: Topic :: Software Development :: Libraries :: pygame
Classifier: Programming Language :: Python
Classifier: Programming Language :: Python :: 3
Classifier: Programming Language :: Python :: 3.4
Classifier: Programming Language :: Python :: 3.5
Classifier: Programming Language :: Python :: 3.6
Requires-Dist: psutil (>=5.4.1)
Requires-Dist: pygame (>=1.9.3)
